payme/__init__.py
payme/hasher.py
payme-0.2.0.dist-info/LICENCE
payme-0.2.0.dist-info/METADATA
payme-0.2.0.dist-info/WHEEL
payme-0.2.0.dist-info/top_level.txt
payme-0.2.0.dist-info/RECORD
