Metadata-Version: 2.1
Name: payme
Version: 0.2.0
Summary: PayU Money Payment Gateway integration utilities
Home-page: http://github.com/dsfx3d/pay-me
Author: dsfx3d
Author-email: dsfx3d@gmail.com
License: MIT
Keywords: payment gateway india integration
Platform: UNKNOWN
Classifier: Development Status :: 3 - Alpha
Classifier: License :: OSI Approved :: MIT License
